aws_ecs_cluster/__init__.py
aws_ecs_cluster/ecs_cluster.py
aws_ecs_cluster/package/__init__.py
aws_ecs_cluster/package/action.py
aws_ecs_cluster/package/cfnresponse.py
aws_ecs_cluster/package/index.py
aws_ecs_cluster-1.3.0.dist-info/LICENSE
aws_ecs_cluster-1.3.0.dist-info/METADATA
aws_ecs_cluster-1.3.0.dist-info/WHEEL
aws_ecs_cluster-1.3.0.dist-info/top_level.txt
aws_ecs_cluster-1.3.0.dist-info/RECORD
